{
  "project_info": {
    "project_number": "692739843757",
    "project_id": "naljalseva-prod-434bd",
    "storage_bucket": "naljalseva-prod-434bd.appspot.com"
  },
  "client": [
    {
      "client_info": {
        "mobilesdk_app_id": "1:692739843757:android:6fc4c4a8d205216e5f4824",
        "android_client_info": {
          "package_name": "com.jjm.naljalseva"
        }
      },
      "oauth_client": [],
      "api_key": [
        {
          "current_key": "AIzaSyC-hOeHQnWqCnW82Y5kKr8RvaioxdlsFSk"
        }
      ],
      "services": {
        "appinvite_service": {
          "other_platform_oauth_client": []
        }
      }
    }
  ],
  "configuration_version": "1"
}